uraeus.smbd-0.0.1.dev3-py3.7-nspkg.pth
uraeus/smbd/__init__.py
uraeus/smbd/systems.py
uraeus/smbd/symbolic/__init__.py
uraeus/smbd/symbolic/components/__init__.py
uraeus/smbd/symbolic/components/algebraic_constraints.py
uraeus/smbd/symbolic/components/bodies.py
uraeus/smbd/symbolic/components/constraints_equations.py
uraeus/smbd/symbolic/components/forces.py
uraeus/smbd/symbolic/components/helpers.py
uraeus/smbd/symbolic/components/joints.py
uraeus/smbd/symbolic/components/matrices.py
uraeus/smbd/symbolic/components/tests.py
uraeus/smbd/symbolic/systems/__init__.py
uraeus/smbd/symbolic/systems/configuration_classes.py
uraeus/smbd/symbolic/systems/topology_classes.py
uraeus/smbd/utilities/__init__.py
uraeus/smbd/utilities/interfaces/__init__.py
uraeus/smbd/utilities/interfaces/_decorated_containers.py
uraeus/smbd/utilities/interfaces/config.py
uraeus/smbd/utilities/interfaces/nbgens.py
uraeus/smbd/utilities/interfaces/projects.py
uraeus/smbd/utilities/interfaces/systems.py
uraeus/smbd/utilities/serialization/__init__.py
uraeus/smbd/utilities/serialization/structural/__init__.py
uraeus/smbd/utilities/serialization/structural/json/__init__.py
uraeus/smbd/utilities/serialization/structural/json/assembly_encoder.py
uraeus/smbd/utilities/serialization/structural/json/configuration_encoder.py
uraeus.smbd-0.0.1.dev3.dist-info/LICENSE
uraeus.smbd-0.0.1.dev3.dist-info/METADATA
uraeus.smbd-0.0.1.dev3.dist-info/WHEEL
uraeus.smbd-0.0.1.dev3.dist-info/namespace_packages.txt
uraeus.smbd-0.0.1.dev3.dist-info/top_level.txt
uraeus.smbd-0.0.1.dev3.dist-info/RECORD
