Metadata-Version: 2.1
Name: uraeus.smbd
Version: 0.0.1.dev3
Summary: A python package for symbolic creation and analysis of constrained multi-body systems.
Home-page: https://github.com/khaledghobashy/uraeus-smbd
Author: Khaled Ghobashy
Author-email: khaled.ghobashy@live.com
License: UNKNOWN
Platform: UNKNOWN
Classifier: Programming Language :: Python :: 3
Classifier: License :: OSI Approved :: BSD License
Classifier: Operating System :: OS Independent
Classifier: Development Status :: 1 - Planning
Classifier: Intended Audience :: Education
Classifier: Intended Audience :: Science/Research
Classifier: Topic :: Scientific/Engineering
Classifier: Topic :: Scientific/Engineering :: Physics
Classifier: Topic :: Scientific/Engineering :: Mathematics
Requires-Python: >=3.6
Requires-Dist: sympy (==1.4)
Requires-Dist: networkx
Requires-Dist: cloudpickle
Requires-Dist: matplotlib
